[
  {"id": 1, "name": "Jeremiah Smith", "position": "WR", "school": "Ohio State", "city": "Hollywood", "state": "FL", "stars": 5, "rating": 0.9998, "ranking": 1, "stateRanking": 1, "positionRanking": 1},
  {"id": 2, "name": "Dylan Raiola", "position": "QB", "school": "Nebraska", "city": "Chandler", "state": "AZ", "stars": 5, "rating": 0.9996, "ranking": 2, "stateRanking": 1, "positionRanking": 1},
  {"id": 3, "name": "Kam Dewberry", "position": "OG", "school": "Texas A&M", "city": "Humble", "state": "TX", "stars": 5, "rating": 0.9991, "ranking": 3, "stateRanking": 1, "positionRanking": 1},
  {"id": 4, "name": "Mykel Williams", "position": "DL", "school": "Georgia", "city": "Columbus", "state": "GA", "stars": 5, "rating": 0.9989, "ranking": 4, "stateRanking": 1, "positionRanking": 1},
  {"id": 5, "name": "David Hicks", "position": "DT", "school": "Texas", "city": "Allen", "state": "TX", "stars": 5, "rating": 0.9988, "ranking": 5, "stateRanking": 2, "positionRanking": 1},
  {"id": 6, "name": "Ryan Wingo", "position": "WR", "school": "Texas", "city": "St. Louis", "state": "MO", "stars": 5, "rating": 0.9985, "ranking": 6, "stateRanking": 1, "positionRanking": 2},
  {"id": 7, "name": "Colin Simmons", "position": "EDGE", "school": "Texas", "city": "Duncanville", "state": "TX", "stars": 5, "rating": 0.9983, "ranking": 7, "stateRanking": 3, "positionRanking": 1},
  {"id": 8, "name": "Nico Iamaleava", "position": "QB", "school": "Tennessee", "city": "Long Beach", "state": "CA", "stars": 5, "rating": 0.9981, "ranking": 8, "stateRanking": 1, "positionRanking": 2},
  {"id": 9, "name": "KJ Bolden", "position": "S", "school": "Georgia", "city": "Buford", "state": "GA", "stars": 5, "rating": 0.9979, "ranking": 9, "stateRanking": 2, "positionRanking": 1},
  {"id": 10, "name": "Kade Renfro", "position": "QB", "school": "Ole Miss", "city": "Starkville", "state": "MS", "stars": 5, "rating": 0.9975, "ranking": 10, "stateRanking": 1, "positionRanking": 3},
  {"id": 11, "name": "Desmond Ricks", "position": "CB", "school": "LSU", "city": "Bradenton", "state": "FL", "stars": 5, "rating": 0.9972, "ranking": 11, "stateRanking": 2, "positionRanking": 1},
  {"id": 12, "name": "Jayden Wayne", "position": "EDGE", "school": "Michigan", "city": "Bradenton", "state": "FL", "stars": 5, "rating": 0.9969, "ranking": 12, "stateRanking": 3, "positionRanking": 2},
  {"id": 13, "name": "Peter Woods", "position": "DT", "school": "Alabama", "city": "Thompson", "state": "AL", "stars": 5, "rating": 0.9967, "ranking": 13, "stateRanking": 1, "positionRanking": 2},
  {"id": 14, "name": "Peyton Bowen", "position": "S", "school": "Oregon", "city": "Denton", "state": "TX", "stars": 5, "rating": 0.9964, "ranking": 14, "stateRanking": 4, "positionRanking": 2},
  {"id": 15, "name": "Caleb Downs", "position": "S", "school": "Alabama", "city": "Hoschton", "state": "GA", "stars": 5, "rating": 0.9962, "ranking": 15, "stateRanking": 3, "positionRanking": 3},
  {"id": 16, "name": "Jaden Rashada", "position": "QB", "school": "Arizona State", "city": "Pittsburg", "state": "CA", "stars": 5, "rating": 0.9958, "ranking": 16, "stateRanking": 2, "positionRanking": 4},
  {"id": 17, "name": "Jordan Seaton", "position": "OT", "school": "Colorado", "city": "Washington", "state": "DC", "stars": 5, "rating": 0.9955, "ranking": 17, "stateRanking": 1, "positionRanking": 1},
  {"id": 18, "name": "Kelvin Banks Jr.", "position": "OT", "school": "Texas", "city": "Humble", "state": "TX", "stars": 5, "rating": 0.9952, "ranking": 18, "stateRanking": 5, "positionRanking": 2},
  {"id": 19, "name": "Carnell Tate", "position": "WR", "school": "Ohio State", "city": "Bradenton", "state": "FL", "stars": 5, "rating": 0.9948, "ranking": 19, "stateRanking": 4, "positionRanking": 3},
  {"id": 20, "name": "Cormani McClain", "position": "CB", "school": "Colorado", "city": "Lakeland", "state": "FL", "stars": 5, "rating": 0.9945, "ranking": 20, "stateRanking": 5, "positionRanking": 2},
  {"id": 21, "name": "Samson Okunlola", "position": "OT", "school": "Miami", "city": "Thayer", "state": "MA", "stars": 5, "rating": 0.9942, "ranking": 21, "stateRanking": 1, "positionRanking": 3},
  {"id": 22, "name": "Justin Muckelroy", "position": "ATH", "school": "Alabama", "city": "Muscle Shoals", "state": "AL", "stars": 5, "rating": 0.9938, "ranking": 22, "stateRanking": 2, "positionRanking": 1},
  {"id": 23, "name": "Kadyn Proctor", "position": "OT", "school": "Iowa", "city": "Des Moines", "state": "IA", "stars": 5, "rating": 0.9935, "ranking": 23, "stateRanking": 1, "positionRanking": 4},
  {"id": 24, "name": "Derek Williams", "position": "WR", "school": "LSU", "city": "San Diego", "state": "CA", "stars": 5, "rating": 0.9931, "ranking": 24, "stateRanking": 3, "positionRanking": 4},
  {"id": 25, "name": "Nyckoles Harbor", "position": "EDGE", "school": "South Carolina", "city": "Washington", "state": "DC", "stars": 5, "rating": 0.9928, "ranking": 25, "stateRanking": 2, "positionRanking": 3},
  {"id": 26, "name": "Tony Mitchell", "position": "CB", "school": "Alabama", "city": "Thompson", "state": "AL", "stars": 5, "rating": 0.9924, "ranking": 26, "stateRanking": 3, "positionRanking": 3},
  {"id": 27, "name": "Duce Robinson", "position": "TE", "school": "USC", "city": "Phoenix", "state": "AZ", "stars": 5, "rating": 0.9921, "ranking": 27, "stateRanking": 2, "positionRanking": 1},
  {"id": 28, "name": "Jalen Hale", "position": "WR", "school": "Texas", "city": "Longview", "state": "TX", "stars": 5, "rating": 0.9918, "ranking": 28, "stateRanking": 6, "positionRanking": 5},
  {"id": 29, "name": "Malik Muhammad", "position": "CB", "school": "Texas", "city": "Dallas", "state": "TX", "stars": 5, "rating": 0.9914, "ranking": 29, "stateRanking": 7, "positionRanking": 4},
  {"id": 30, "name": "Francis Mauigoa", "position": "OG", "school": "Miami", "city": "Bradenton", "state": "FL", "stars": 5, "rating": 0.9911, "ranking": 30, "stateRanking": 6, "positionRanking": 2},
  {"id": 31, "name": "Brandon Inniss", "position": "WR", "school": "Ohio State", "city": "Fort Lauderdale", "state": "FL", "stars": 4, "rating": 0.9905, "ranking": 31, "stateRanking": 7, "positionRanking": 6},
  {"id": 32, "name": "Kayden McDonald", "position": "DT", "school": "Clemson", "city": "North Augusta", "state": "SC", "stars": 4, "rating": 0.9901, "ranking": 32, "stateRanking": 1, "positionRanking": 3},
  {"id": 33, "name": "Johnathan Echols", "position": "LB", "school": "Georgia", "city": "Covington", "state": "GA", "stars": 4, "rating": 0.9898, "ranking": 33, "stateRanking": 4, "positionRanking": 1},
  {"id": 34, "name": "Derrick LeBlanc", "position": "DL", "school": "Oklahoma", "city": "Osceola", "state": "FL", "stars": 4, "rating": 0.9894, "ranking": 34, "stateRanking": 8, "positionRanking": 2},
  {"id": 35, "name": "Dylan Edwards", "position": "RB", "school": "Colorado", "city": "Derby", "state": "KS", "stars": 4, "rating": 0.9891, "ranking": 35, "stateRanking": 1, "positionRanking": 1},
  {"id": 36, "name": "Rueben Owens II", "position": "RB", "school": "Texas A&M", "city": "El Campo", "state": "TX", "stars": 4, "rating": 0.9887, "ranking": 36, "stateRanking": 8, "positionRanking": 2},
  {"id": 37, "name": "Nathaniel Joseph", "position": "WR", "school": "Clemson", "city": "Miami", "state": "FL", "stars": 4, "rating": 0.9884, "ranking": 37, "stateRanking": 9, "positionRanking": 7},
  {"id": 38, "name": "Air Noland", "position": "QB", "school": "Ohio State", "city": "Fairburn", "state": "GA", "stars": 4, "rating": 0.9880, "ranking": 38, "stateRanking": 5, "positionRanking": 5},
  {"id": 39, "name": "DJ Lagway", "position": "QB", "school": "Florida", "city": "Willis", "state": "TX", "stars": 5, "rating": 0.9876, "ranking": 39, "stateRanking": 9, "positionRanking": 6},
  {"id": 40, "name": "Johntay Cook II", "position": "WR", "school": "Texas", "city": "DeSoto", "state": "TX", "stars": 4, "rating": 0.9872, "ranking": 40, "stateRanking": 10, "positionRanking": 8},
  {"id": 41, "name": "Qua Russaw", "position": "EDGE", "school": "Alabama", "city": "Phenix City", "state": "AL", "stars": 5, "rating": 0.9868, "ranking": 41, "stateRanking": 4, "positionRanking": 4},
  {"id": 42, "name": "James Smith", "position": "DL", "school": "Alabama", "city": "Montgomery", "state": "AL", "stars": 5, "rating": 0.9865, "ranking": 42, "stateRanking": 5, "positionRanking": 3},
  {"id": 43, "name": "TJ Shanahan", "position": "OG", "school": "Texas", "city": "Austin", "state": "TX", "stars": 4, "rating": 0.9861, "ranking": 43, "stateRanking": 11, "positionRanking": 3},
  {"id": 44, "name": "Raul Aguirre", "position": "OT", "school": "Ohio State", "city": "San Antonio", "state": "TX", "stars": 4, "rating": 0.9858, "ranking": 44, "stateRanking": 12, "positionRanking": 5},
  {"id": 45, "name": "CJ Carr", "position": "QB", "school": "Notre Dame", "city": "Saline", "state": "MI", "stars": 4, "rating": 0.9854, "ranking": 45, "stateRanking": 1, "positionRanking": 7},
  {"id": 46, "name": "Jalen Brown", "position": "WR", "school": "LSU", "city": "Miami", "state": "FL", "stars": 4, "rating": 0.9850, "ranking": 46, "stateRanking": 10, "positionRanking": 9},
  {"id": 47, "name": "Elijah Griffin", "position": "EDGE", "school": "USC", "city": "Alpharetta", "state": "GA", "stars": 4, "rating": 0.9847, "ranking": 47, "stateRanking": 6, "positionRanking": 5},
  {"id": 48, "name": "Richard Young", "position": "RB", "school": "Alabama", "city": "Lehigh Acres", "state": "FL", "stars": 4, "rating": 0.9843, "ranking": 48, "stateRanking": 11, "positionRanking": 3},
  {"id": 49, "name": "Jason Moore", "position": "DL", "school": "Michigan", "city": "Hyattsville", "state": "MD", "stars": 4, "rating": 0.9839, "ranking": 49, "stateRanking": 1, "positionRanking": 4},
  {"id": 50, "name": "Kahlil Benson", "position": "DT", "school": "Michigan", "city": "Baltimore", "state": "MD", "stars": 4, "rating": 0.9836, "ranking": 50, "stateRanking": 2, "positionRanking": 4},
  {"id": 51, "name": "Matayo Uiagalelei", "position": "EDGE", "school": "Oregon", "city": "Bellflower", "state": "CA", "stars": 4, "rating": 0.9832, "ranking": 51, "stateRanking": 4, "positionRanking": 6},
  {"id": 52, "name": "Benjamin Perry", "position": "OT", "school": "Georgia", "city": "Nashville", "state": "TN", "stars": 4, "rating": 0.9828, "ranking": 52, "stateRanking": 1, "positionRanking": 6},
  {"id": 53, "name": "Devin Brown", "position": "QB", "school": "Ohio State", "city": "Draper", "state": "UT", "stars": 4, "rating": 0.9825, "ranking": 53, "stateRanking": 1, "positionRanking": 8},
  {"id": 54, "name": "Ty Lockwood", "position": "TE", "school": "Alabama", "city": "Thompson Station", "state": "TN", "stars": 4, "rating": 0.9821, "ranking": 54, "stateRanking": 2, "positionRanking": 2},
  {"id": 55, "name": "Dante Moore", "position": "QB", "school": "UCLA", "city": "Detroit", "state": "MI", "stars": 5, "rating": 0.9818, "ranking": 55, "stateRanking": 2, "positionRanking": 9},
  {"id": 56, "name": "Connor Colby", "position": "OG", "school": "Iowa", "city": "Cedar Rapids", "state": "IA", "stars": 4, "rating": 0.9814, "ranking": 56, "stateRanking": 2, "positionRanking": 4},
  {"id": 57, "name": "Eddrick Houston", "position": "EDGE", "school": "USC", "city": "Buford", "state": "GA", "stars": 4, "rating": 0.9810, "ranking": 57, "stateRanking": 7, "positionRanking": 7},
  {"id": 58, "name": "Jeremiah Alexander", "position": "LB", "school": "Alabama", "city": "Thompson", "state": "AL", "stars": 4, "rating": 0.9807, "ranking": 58, "stateRanking": 6, "positionRanking": 2},
  {"id": 59, "name": "Kyngstonn Viliamu-Asa", "position": "DL", "school": "Oregon", "city": "Henderson", "state": "NV", "stars": 4, "rating": 0.9803, "ranking": 59, "stateRanking": 1, "positionRanking": 5},
  {"id": 60, "name": "Samuel M'Pemba", "position": "EDGE", "school": "Notre Dame", "city": "Bradenton", "state": "FL", "stars": 4, "rating": 0.9799, "ranking": 60, "stateRanking": 12, "positionRanking": 8},
  {"id": 61, "name": "Jaylen Mbakwe", "position": "DT", "school": "Michigan", "city": "Fort Washington", "state": "MD", "stars": 4, "rating": 0.9795, "ranking": 61, "stateRanking": 3, "positionRanking": 5},
  {"id": 62, "name": "Ka'Morreun Pimpton", "position": "DL", "school": "Oklahoma", "city": "Mansfield", "state": "TX", "stars": 4, "rating": 0.9791, "ranking": 62, "stateRanking": 13, "positionRanking": 6},
  {"id": 63, "name": "Markis Deal", "position": "OT", "school": "USC", "city": "Corona", "state": "CA", "stars": 4, "rating": 0.9787, "ranking": 63, "stateRanking": 5, "positionRanking": 7},
  {"id": 64, "name": "Tackett Curtis", "position": "LB", "school": "USC", "city": "Many", "state": "LA", "stars": 4, "rating": 0.9784, "ranking": 64, "stateRanking": 1, "positionRanking": 3},
  {"id": 65, "name": "Andrew Mukuba", "position": "S", "school": "Clemson", "city": "Austin", "state": "TX", "stars": 4, "rating": 0.9780, "ranking": 65, "stateRanking": 14, "positionRanking": 4},
  {"id": 66, "name": "London Humphreys", "position": "WR", "school": "Georgia", "city": "Brentwood", "state": "TN", "stars": 4, "rating": 0.9776, "ranking": 66, "stateRanking": 3, "positionRanking": 10},
  {"id": 67, "name": "Raymond Cottrell", "position": "WR", "school": "Florida", "city": "Milton", "state": "FL", "stars": 4, "rating": 0.9772, "ranking": 67, "stateRanking": 13, "positionRanking": 11},
  {"id": 68, "name": "Javien Toviano", "position": "CB", "school": "LSU", "city": "Arlington", "state": "TX", "stars": 4, "rating": 0.9769, "ranking": 68, "stateRanking": 15, "positionRanking": 5},
  {"id": 69, "name": "Luke Hasz", "position": "TE", "school": "Arkansas", "city": "Bixby", "state": "OK", "stars": 4, "rating": 0.9765, "ranking": 69, "stateRanking": 1, "positionRanking": 3},
  {"id": 70, "name": "Jayden Gibson", "position": "WR", "school": "Florida", "city": "Orlando", "state": "FL", "stars": 4, "rating": 0.9761, "ranking": 70, "stateRanking": 14, "positionRanking": 12},
  {"id": 71, "name": "Daejon Reynolds", "position": "WR", "school": "Oregon", "city": "Jacksonville", "state": "FL", "stars": 4, "rating": 0.9757, "ranking": 71, "stateRanking": 15, "positionRanking": 13},
  {"id": 72, "name": "Ellis Robinson IV", "position": "CB", "school": "Clemson", "city": "New Haven", "state": "CT", "stars": 4, "rating": 0.9753, "ranking": 72, "stateRanking": 1, "positionRanking": 6},
  {"id": 73, "name": "Derek Meadows", "position": "OT", "school": "Ohio State", "city": "Franklin", "state": "TN", "stars": 4, "rating": 0.9749, "ranking": 73, "stateRanking": 4, "positionRanking": 8},
  {"id": 74, "name": "Caleb Herring", "position": "LB", "school": "Ohio State", "city": "Baton Rouge", "state": "LA", "stars": 4, "rating": 0.9746, "ranking": 74, "stateRanking": 2, "positionRanking": 4},
  {"id": 75, "name": "Jayvon Thomas", "position": "RB", "school": "Oregon", "city": "Richmond", "state": "TX", "stars": 4, "rating": 0.9742, "ranking": 75, "stateRanking": 16, "positionRanking": 4},
  {"id": 76, "name": "Collins Acheampong", "position": "EDGE", "school": "USC", "city": "Suwanee", "state": "GA", "stars": 4, "rating": 0.9738, "ranking": 76, "stateRanking": 8, "positionRanking": 9},
  {"id": 77, "name": "Kayin Lee", "position": "CB", "school": "Georgia", "city": "Ellenwood", "state": "GA", "stars": 4, "rating": 0.9734, "ranking": 77, "stateRanking": 9, "positionRanking": 7},
  {"id": 78, "name": "Devin Sanchez", "position": "CB", "school": "Texas A&M", "city": "New Caney", "state": "TX", "stars": 4, "rating": 0.9730, "ranking": 78, "stateRanking": 17, "positionRanking": 8},
  {"id": 79, "name": "Josh Conerly Jr.", "position": "OT", "school": "Oregon", "city": "Seattle", "state": "WA", "stars": 4, "rating": 0.9727, "ranking": 79, "stateRanking": 1, "positionRanking": 9},
  {"id": 80, "name": "David Stone", "position": "DT", "school": "Oklahoma", "city": "Oklahoma City", "state": "OK", "stars": 4, "rating": 0.9723, "ranking": 80, "stateRanking": 2, "positionRanking": 6},
  {"id": 81, "name": "Roderick Pierce", "position": "RB", "school": "Michigan", "city": "Chicago", "state": "IL", "stars": 4, "rating": 0.9719, "ranking": 81, "stateRanking": 1, "positionRanking": 5},
  {"id": 82, "name": "Trammel Jones Jr.", "position": "S", "school": "Ohio State", "city": "McKinney", "state": "TX", "stars": 4, "rating": 0.9715, "ranking": 82, "stateRanking": 18, "positionRanking": 5},
  {"id": 83, "name": "Joenel Aguero", "position": "S", "school": "Miami", "city": "Lynn", "state": "MA", "stars": 4, "rating": 0.9711, "ranking": 83, "stateRanking": 2, "positionRanking": 6},
  {"id": 84, "name": "Terrance Love", "position": "WR", "school": "Alabama", "city": "Daphne", "state": "AL", "stars": 4, "rating": 0.9708, "ranking": 84, "stateRanking": 7, "positionRanking": 14},
  {"id": 85, "name": "Deshawn Warner", "position": "LB", "school": "Oregon", "city": "Inglewood", "state": "CA", "stars": 4, "rating": 0.9704, "ranking": 85, "stateRanking": 6, "positionRanking": 5},
  {"id": 86, "name": "Jalen Wiggins", "position": "WR", "school": "Clemson", "city": "Birmingham", "state": "AL", "stars": 4, "rating": 0.9700, "ranking": 86, "stateRanking": 8, "positionRanking": 15},
  {"id": 87, "name": "Shamar Arnoux", "position": "DL", "school": "Georgia", "city": "Lakeland", "state": "FL", "stars": 4, "rating": 0.9696, "ranking": 87, "stateRanking": 16, "positionRanking": 7},
  {"id": 88, "name": "Isaiah Bond", "position": "WR", "school": "Alabama", "city": "Buford", "state": "GA", "stars": 4, "rating": 0.9692, "ranking": 88, "stateRanking": 10, "positionRanking": 16},
  {"id": 89, "name": "Antwann Hill Jr.", "position": "DL", "school": "Texas A&M", "city": "Katy", "state": "TX", "stars": 4, "rating": 0.9688, "ranking": 89, "stateRanking": 19, "positionRanking": 8},
  {"id": 90, "name": "Jordan Ross", "position": "OG", "school": "Georgia", "city": "Buford", "state": "GA", "stars": 4, "rating": 0.9685, "ranking": 90, "stateRanking": 11, "positionRanking": 5},
  {"id": 91, "name": "Xavier Nwankpa", "position": "S", "school": "Iowa", "city": "Altoona", "state": "IA", "stars": 4, "rating": 0.9681, "ranking": 91, "stateRanking": 3, "positionRanking": 7},
  {"id": 92, "name": "Tausili Akana", "position": "EDGE", "school": "Utah", "city": "Honolulu", "state": "HI", "stars": 4, "rating": 0.9677, "ranking": 92, "stateRanking": 1, "positionRanking": 10},
  {"id": 93, "name": "Zion Ferguson", "position": "LB", "school": "Notre Dame", "city": "Orlando", "state": "FL", "stars": 4, "rating": 0.9673, "ranking": 93, "stateRanking": 17, "positionRanking": 6},
  {"id": 94, "name": "Kamari Wilson", "position": "S", "school": "Florida", "city": "Fort Pierce", "state": "FL", "stars": 4, "rating": 0.9669, "ranking": 94, "stateRanking": 18, "positionRanking": 8},
  {"id": 95, "name": "Kaven Call", "position": "DT", "school": "Oklahoma", "city": "Owasso", "state": "OK", "stars": 4, "rating": 0.9666, "ranking": 95, "stateRanking": 3, "positionRanking": 7},
  {"id": 96, "name": "Tyler Turner", "position": "OT", "school": "Texas", "city": "Waco", "state": "TX", "stars": 4, "rating": 0.9662, "ranking": 96, "stateRanking": 20, "positionRanking": 10},
  {"id": 97, "name": "Jerrick Gibson", "position": "RB", "school": "Alabama", "city": "Gainesville", "state": "GA", "stars": 4, "rating": 0.9658, "ranking": 97, "stateRanking": 12, "positionRanking": 6},
  {"id": 98, "name": "Jyaire Hill", "position": "CB", "school": "Ohio State", "city": "Independence", "state": "KY", "stars": 4, "rating": 0.9654, "ranking": 98, "stateRanking": 1, "positionRanking": 9},
  {"id": 99, "name": "Demon Williams", "position": "OT", "school": "Florida State", "city": "Jefferson", "state": "GA", "stars": 4, "rating": 0.9650, "ranking": 99, "stateRanking": 13, "positionRanking": 11},
  {"id": 100, "name": "AJ Harris", "position": "CB", "school": "Alabama", "city": "Glenarden", "state": "MD", "stars": 4, "rating": 0.9647, "ranking": 100, "stateRanking": 4, "positionRanking": 10}
]
